heinlein/__init__.py
heinlein/api/__init__.py
heinlein/api/_cmds.py
heinlein/cmds.py
heinlein/config/__init__.py
heinlein/config/cmds.json
heinlein/config/config.json
heinlein/config/config.py
heinlein/config/default.json
heinlein/config/dtypes/catalog.json
heinlein/config/dtypes/dtypes.json
heinlein/config/region/region.json
heinlein/dataset/__init__.py
heinlein/dataset/dataset.py
heinlein/dataset/extension.py
heinlein/dtypes/__init__.py
heinlein/dtypes/catalog.py
heinlein/dtypes/dobj.py
heinlein/dtypes/handlers/__init__.py
heinlein/dtypes/handlers/catalog.py
heinlein/dtypes/handlers/handler.py
heinlein/dtypes/handlers/mask.py
heinlein/dtypes/handlers/utilities.py
heinlein/dtypes/mask.py
heinlein/entrypoint.py
heinlein/errors.py
heinlein/locations.py
heinlein/manager/__init__.py
heinlein/manager/cache.py
heinlein/manager/manager.py
heinlein/region/__init__.py
heinlein/region/base.py
heinlein/region/footprint.py
heinlein/region/region.py
heinlein/region/sampling.py
heinlein/utilities/__init__.py
heinlein/utilities/prep.py
heinlein/utilities/utilities.py
heinlein-0.10.11.dist-info/METADATA
heinlein-0.10.11.dist-info/WHEEL
heinlein-0.10.11.dist-info/entry_points.txt
heinlein-0.10.11.dist-info/RECORD
