Metadata-Version: 2.3
Name: heinlein
Version: 0.10.11
Summary: 
Author: Patrick Wells
Author-email: patrick@astropatty.com
Requires-Python: >=3.11
Classifier: Programming Language :: Python :: 3
Classifier: Programming Language :: Python :: 3.11
Classifier: Programming Language :: Python :: 3.12
Classifier: Programming Language :: Python :: 3.13
Provides-Extra: cfht
Provides-Extra: des
Provides-Extra: hsc
Provides-Extra: ms
Requires-Dist: appdirs (>=1.4.4,<2.0)
Requires-Dist: astropy (>=7.0.1,<8.0.0)
Requires-Dist: cacheout (>=0.16.0,<1.0)
Requires-Dist: click (>=8.1.7,<9.0)
Requires-Dist: dynaconf (>=3.2.4,<4.0)
Requires-Dist: healpy (>=1.18.0,<2.0.0)
Requires-Dist: heinlein-cfht (>=0.1.0) ; extra == "cfht"
Requires-Dist: heinlein-des (>=0.1.2) ; extra == "des"
Requires-Dist: heinlein-hsc (>=0.1.0) ; extra == "hsc"
Requires-Dist: heinlein-ms (>=0.1.0) ; extra == "ms"
Requires-Dist: numpy (>=2.2.0,<3.0)
Requires-Dist: pandas (>=2.2.0,<3.0)
Requires-Dist: portalocker (>=2.8.2,<3.0)
Requires-Dist: pydantic (>=2.10.6,<3.0.0)
Requires-Dist: pydantic-settings (>=2.7.1,<3.0.0)
Requires-Dist: pyerfa (>=2.0.1.5,<3.0.0.0)
Requires-Dist: regions (>=0.8,<1.0)
Requires-Dist: shapely (>=2.0.2,<3.0)
Requires-Dist: spherical-geometry (>=1.3.0,<2.0)
Requires-Dist: sqlalchemy (>=2.0.25,<3.0)
